LICENSE
MANIFEST.in
README.md
pyproject.toml
setup.cfg
setup.py
budibase_client/__init__.py
budibase_client/budibase_client.py
budibase_client.egg-info/PKG-INFO
budibase_client.egg-info/SOURCES.txt
budibase_client.egg-info/dependency_links.txt
budibase_client.egg-info/requires.txt
budibase_client.egg-info/top_level.txt