Metadata-Version: 2.1
Name: budibase-client
Version: 0.1.1
Summary: A lightweight client for budibase
Home-page: https://gitlab.com/idcohorts/Python-Packages/budibase-python-client
Author: Nick Schulze
Author-email: nick.schulze@uk-koeln.de
License: MIT
Keywords: budibase,client,api
Platform: UNKNOWN
License-File: LICENSE
